splicejunxchx/__init__.py
splicejunxchx/constitutive_exons.py
splicejunxchx/extract_splice_junctions.py
splicejunxchx/func_file.py
splicejunxchx/get_seq_splicesite.py
splicejunxchx/maxent.py
splicejunxchx/splicejunxchx.py
splicejunxchx-2.8.dist-info/LICENSE
splicejunxchx-2.8.dist-info/METADATA
splicejunxchx-2.8.dist-info/WHEEL
splicejunxchx-2.8.dist-info/entry_points.txt
splicejunxchx-2.8.dist-info/top_level.txt
splicejunxchx-2.8.dist-info/RECORD
