Metadata-Version: 2.1
Name: splicejunxchx
Version: 2.8
Summary: characterize the splice junctions outputted by SJ.out.tab file
Home-page: https://github.com/ayushkumar-umms/splice-junction-characterization
Author: Ayush Kumar
Author-email: ayush.kumar@umassmed.edu
License: MIT
Keywords: splicing
Platform: UNKNOWN
Classifier: Operating System :: OS Independent
Classifier: Intended Audience :: Developers
Classifier: Topic :: Internet
Classifier: License :: OSI Approved :: MIT License
Classifier: Programming Language :: Python :: 3.6
Requires-Python: >=3.6
